[
  {
    "image_name": "image5000.png",
    "position_of_policman": "вправо",
    "what_to_do": "стоп"
  },
  {
    "image_name": "image5001.png",
    "position_of_policman": "вправо",
    "what_to_do": "стоп"
  },
  {
    "image_name": "image5002.png",
    "position_of_policman": "вправо",
    "what_to_do": "стоп"
  },
  {
    "image_name": "image5003.png",
    "position_of_policman": "вправо",
    "what_to_do": "стоп"
  },
  {
    "image_name": "image5004.png",
    "position_of_policman": "вправо",
    "what_to_do": "стоп"
  },
  {
    "image_name": "image5005.png",
    "position_of_policman": "вправо",
    "what_to_do": "стоп"
  },
  {
    "image_name": "image5006.png",
    "position_of_policman": "вправо",
    "what_to_do": "стоп"
  },
  {
    "image_name": "image5007.png",
    "position_of_policman": "вправо",
    "what_to_do": "стоп"
  },
  {
    "image_name": "image5008.png",
    "position_of_policman": "вправо",
    "what_to_do": "стоп"
  },
  {
    "image_name": "image5009.png",
    "position_of_policman": "вправо",
    "what_to_do": "стоп"
  },
  {
    "image_name": "image5010.png",
    "position_of_policman": "вправо",
    "what_to_do": "стоп"
  },
  {
    "image_name": "image5011.png",
    "position_of_policman": "вправо",
    "what_to_do": "стоп"
  },
  {
    "image_name": "image5012.png",
    "position_of_policman": "вправо",
    "what_to_do": "стоп"
  },
  {
    "image_name": "image5013.png",
    "position_of_policman": "вправо",
    "what_to_do": "стоп"
  },
  {
    "image_name": "image5014.png",
    "position_of_policman": "вправо",
    "what_to_do": "стоп"
  },
  {
    "image_name": "image5015.png",
    "position_of_policman": "вправо",
    "what_to_do": "стоп"
  },
  {
    "image_name": "image5016.png",
    "position_of_policman": "вправо",
    "what_to_do": "стоп"
  },
  {
    "image_name": "image5017.png",
    "position_of_policman": "вправо",
    "what_to_do": "стоп"
  },
  {
    "image_name": "image5018.png",
    "position_of_policman": "вправо",
    "what_to_do": "стоп"
  },
  {
    "image_name": "image5019.png",
    "position_of_policman": "вправо",
    "what_to_do": "стоп"
  },
  {
    "image_name": "image5020.png",
    "position_of_policman": "вправо",
    "what_to_do": "стоп"
  },
  {
    "image_name": "image5021.png",
    "position_of_policman": "вправо",
    "what_to_do": "стоп"
  },
  {
    "image_name": "image5022.png",
    "position_of_policman": "вправо",
    "what_to_do": "стоп"
  },
  {
    "image_name": "image5023.png",
    "position_of_policman": "вправо",
    "what_to_do": "стоп"
  },
  {
    "image_name": "image5024.png",
    "position_of_policman": "вправо",
    "what_to_do": "стоп"
  },
  {
    "image_name": "image5025.png",
    "position_of_policman": "вправо",
    "what_to_do": "стоп"
  },
  {
    "image_name": "image5026.png",
    "position_of_policman": "вправо",
    "what_to_do": "стоп"
  },
  {
    "image_name": "image5027.png",
    "position_of_policman": "вправо",
    "what_to_do": "стоп"
  },
  {
    "image_name": "image5028.png",
    "position_of_policman": "вправо",
    "what_to_do": "стоп"
  },
  {
    "image_name": "image5029.png",
    "position_of_policman": "вправо",
    "what_to_do": "стоп"
  },
  {
    "image_name": "image5030.png",
    "position_of_policman": "вправо",
    "what_to_do": "стоп"
  },
  {
    "image_name": "image5031.png",
    "position_of_policman": "вправо",
    "what_to_do": "стоп"
  },
  {
    "image_name": "image5032.png",
    "position_of_policman": "вправо",
    "what_to_do": "стоп"
  },
  {
    "image_name": "image5033.png",
    "position_of_policman": "вправо",
    "what_to_do": "стоп"
  },
  {
    "image_name": "image5034.png",
    "position_of_policman": "вправо",
    "what_to_do": "стоп"
  },
  {
    "image_name": "image5035.png",
    "position_of_policman": "вправо",
    "what_to_do": "стоп"
  },
  {
    "image_name": "image5036.png",
    "position_of_policman": "вправо",
    "what_to_do": "стоп"
  },
  {
    "image_name": "image5037.png",
    "position_of_policman": "вправо",
    "what_to_do": "стоп"
  },
  {
    "image_name": "image5038.png",
    "position_of_policman": "вправо",
    "what_to_do": "стоп"
  },
  {
    "image_name": "image5039.png",
    "position_of_policman": "вправо",
    "what_to_do": "стоп"
  },
  {
    "image_name": "image5040.png",
    "position_of_policman": "вправо",
    "what_to_do": "стоп"
  },
  {
    "image_name": "image5041.png",
    "position_of_policman": "вправо",
    "what_to_do": "стоп"
  },
  {
    "image_name": "image5042.png",
    "position_of_policman": "вправо",
    "what_to_do": "стоп"
  },
  {
    "image_name": "image5043.png",
    "position_of_policman": "вправо",
    "what_to_do": "стоп"
  },
  {
    "image_name": "image5044.png",
    "position_of_policman": "вправо",
    "what_to_do": "стоп"
  },
  {
    "image_name": "image5045.png",
    "position_of_policman": "вправо",
    "what_to_do": "стоп"
  },
  {
    "image_name": "image5046.png",
    "position_of_policman": "вправо",
    "what_to_do": "стоп"
  },
  {
    "image_name": "image5047.png",
    "position_of_policman": "вправо",
    "what_to_do": "стоп"
  },
  {
    "image_name": "image5048.png",
    "position_of_policman": "вправо",
    "what_to_do": "стоп"
  },
  {
    "image_name": "image5049.png",
    "position_of_policman": "вправо",
    "what_to_do": "стоп"
  },
  {
    "image_name": "image5050.png",
    "position_of_policman": "вправо",
    "what_to_do": "стоп"
  },
  {
    "image_name": "image5051.png",
    "position_of_policman": "вправо",
    "what_to_do": "стоп"
  },
  {
    "image_name": "image5052.png",
    "position_of_policman": "вправо",
    "what_to_do": "стоп"
  },
  {
    "image_name": "image5053.png",
    "position_of_policman": "вправо",
    "what_to_do": "стоп"
  },
  {
    "image_name": "image5054.png",
    "position_of_policman": "вправо",
    "what_to_do": "стоп"
  },
  {
    "image_name": "image5055.png",
    "position_of_policman": "вправо",
    "what_to_do": "стоп"
  },
  {
    "image_name": "image5056.png",
    "position_of_policman": "вправо",
    "what_to_do": "стоп"
  },
  {
    "image_name": "image5057.png",
    "position_of_policman": "вправо",
    "what_to_do": "стоп"
  },
  {
    "image_name": "image5058.png",
    "position_of_policman": "вправо",
    "what_to_do": "стоп"
  },
  {
    "image_name": "image5059.png",
    "position_of_policman": "вправо",
    "what_to_do": "стоп"
  },
  {
    "image_name": "image5060.png",
    "position_of_policman": "вправо",
    "what_to_do": "стоп"
  },
  {
    "image_name": "image5061.png",
    "position_of_policman": "вправо",
    "what_to_do": "стоп"
  },
  {
    "image_name": "image5062.png",
    "position_of_policman": "вправо",
    "what_to_do": "стоп"
  },
  {
    "image_name": "image5063.png",
    "position_of_policman": "вправо",
    "what_to_do": "стоп"
  },
  {
    "image_name": "image5064.png",
    "position_of_policman": "вправо",
    "what_to_do": "стоп"
  },
  {
    "image_name": "image5065.png",
    "position_of_policman": "вправо",
    "what_to_do": "стоп"
  },
  {
    "image_name": "image5066.png",
    "position_of_policman": "вправо",
    "what_to_do": "стоп"
  },
  {
    "image_name": "image5067.png",
    "position_of_policman": "вправо",
    "what_to_do": "стоп"
  },
  {
    "image_name": "image5068.png",
    "position_of_policman": "вправо",
    "what_to_do": "стоп"
  },
  {
    "image_name": "image5069.png",
    "position_of_policman": "вправо",
    "what_to_do": "стоп"
  },
  {
    "image_name": "image5070.png",
    "position_of_policman": "вправо",
    "what_to_do": "стоп"
  },
  {
    "image_name": "image5071.png",
    "position_of_policman": "вправо",
    "what_to_do": "стоп"
  },
  {
    "image_name": "image5072.png",
    "position_of_policman": "вправо",
    "what_to_do": "стоп"
  },
  {
    "image_name": "image5073.png",
    "position_of_policman": "вправо",
    "what_to_do": "стоп"
  },
  {
    "image_name": "image5074.png",
    "position_of_policman": "вправо",
    "what_to_do": "стоп"
  },
  {
    "image_name": "image5075.png",
    "position_of_policman": "вправо",
    "what_to_do": "стоп"
  },
  {
    "image_name": "image5076.png",
    "position_of_policman": "вправо",
    "what_to_do": "стоп"
  },
  {
    "image_name": "image5077.png",
    "position_of_policman": "вправо",
    "what_to_do": "стоп"
  },
  {
    "image_name": "image5078.png",
    "position_of_policman": "вправо",
    "what_to_do": "стоп"
  },
  {
    "image_name": "image5079.png",
    "position_of_policman": "вправо",
    "what_to_do": "стоп"
  },
  {
    "image_name": "image5080.png",
    "position_of_policman": "вправо",
    "what_to_do": "стоп"
  },
  {
    "image_name": "image5081.png",
    "position_of_policman": "вправо",
    "what_to_do": "стоп"
  },
  {
    "image_name": "image5082.png",
    "position_of_policman": "вправо",
    "what_to_do": "стоп"
  },
  {
    "image_name": "image5083.png",
    "position_of_policman": "вправо",
    "what_to_do": "стоп"
  },
  {
    "image_name": "image5084.png",
    "position_of_policman": "вправо",
    "what_to_do": "стоп"
  },
  {
    "image_name": "image5085.png",
    "position_of_policman": "вправо",
    "what_to_do": "стоп"
  },
  {
    "image_name": "image5086.png",
    "position_of_policman": "вправо",
    "what_to_do": "стоп"
  },
  {
    "image_name": "image5087.png",
    "position_of_policman": "вправо",
    "what_to_do": "стоп"
  },
  {
    "image_name": "image5088.png",
    "position_of_policman": "вправо",
    "what_to_do": "стоп"
  },
  {
    "image_name": "image5089.png",
    "position_of_policman": "вправо",
    "what_to_do": "стоп"
  },
  {
    "image_name": "image5090.png",
    "position_of_policman": "вправо",
    "what_to_do": "стоп"
  },
  {
    "image_name": "image5091.png",
    "position_of_policman": "вправо",
    "what_to_do": "стоп"
  },
  {
    "image_name": "image5092.png",
    "position_of_policman": "вправо",
    "what_to_do": "стоп"
  },
  {
    "image_name": "image5093.png",
    "position_of_policman": "вправо",
    "what_to_do": "стоп"
  },
  {
    "image_name": "image5094.png",
    "position_of_policman": "вправо",
    "what_to_do": "стоп"
  },
  {
    "image_name": "image5095.png",
    "position_of_policman": "вправо",
    "what_to_do": "стоп"
  },
  {
    "image_name": "image5096.png",
    "position_of_policman": "вправо",
    "what_to_do": "стоп"
  },
  {
    "image_name": "image5097.png",
    "position_of_policman": "вправо",
    "what_to_do": "стоп"
  },
  {
    "image_name": "image5098.png",
    "position_of_policman": "вправо",
    "what_to_do": "стоп"
  },
  {
    "image_name": "image5099.png",
    "position_of_policman": "вправо",
    "what_to_do": "стоп"
  },
  {
    "image_name": "image5100.png",
    "position_of_policman": "вправо",
    "what_to_do": "стоп"
  },
  {
    "image_name": "image5101.png",
    "position_of_policman": "вправо",
    "what_to_do": "стоп"
  },
  {
    "image_name": "image5102.png",
    "position_of_policman": "вправо",
    "what_to_do": "стоп"
  },
  {
    "image_name": "image5103.png",
    "position_of_policman": "вправо",
    "what_to_do": "стоп"
  },
  {
    "image_name": "image5104.png",
    "position_of_policman": "вправо",
    "what_to_do": "стоп"
  },
  {
    "image_name": "image5105.png",
    "position_of_policman": "вправо",
    "what_to_do": "стоп"
  },
  {
    "image_name": "image5106.png",
    "position_of_policman": "вправо",
    "what_to_do": "стоп"
  },
  {
    "image_name": "image5107.png",
    "position_of_policman": "вправо",
    "what_to_do": "стоп"
  },
  {
    "image_name": "image5108.png",
    "position_of_policman": "вправо",
    "what_to_do": "стоп"
  },
  {
    "image_name": "image5109.png",
    "position_of_policman": "вправо",
    "what_to_do": "стоп"
  },
  {
    "image_name": "image5110.png",
    "position_of_policman": "вправо",
    "what_to_do": "стоп"
  },
  {
    "image_name": "image5111.png",
    "position_of_policman": "вправо",
    "what_to_do": "стоп"
  },
  {
    "image_name": "image5112.png",
    "position_of_policman": "вправо",
    "what_to_do": "стоп"
  },
  {
    "image_name": "image5113.png",
    "position_of_policman": "вправо",
    "what_to_do": "стоп"
  },
  {
    "image_name": "image5114.png",
    "position_of_policman": "вправо",
    "what_to_do": "стоп"
  },
  {
    "image_name": "image5115.png",
    "position_of_policman": "вправо",
    "what_to_do": "стоп"
  },
  {
    "image_name": "image5116.png",
    "position_of_policman": "вправо",
    "what_to_do": "стоп"
  },
  {
    "image_name": "image5117.png",
    "position_of_policman": "вправо",
    "what_to_do": "стоп"
  },
  {
    "image_name": "image5118.png",
    "position_of_policman": "вправо",
    "what_to_do": "стоп"
  },
  {
    "image_name": "image5119.png",
    "position_of_policman": "вправо",
    "what_to_do": "стоп"
  },
  {
    "image_name": "image5120.png",
    "position_of_policman": "вправо",
    "what_to_do": "стоп"
  },
  {
    "image_name": "image5121.png",
    "position_of_policman": "вправо",
    "what_to_do": "стоп"
  },
  {
    "image_name": "image5122.png",
    "position_of_policman": "вправо",
    "what_to_do": "стоп"
  },
  {
    "image_name": "image5123.png",
    "position_of_policman": "вправо",
    "what_to_do": "стоп"
  },
  {
    "image_name": "image5124.png",
    "position_of_policman": "вправо",
    "what_to_do": "стоп"
  },
  {
    "image_name": "image5125.png",
    "position_of_policman": "вправо",
    "what_to_do": "стоп"
  },
  {
    "image_name": "image5126.png",
    "position_of_policman": "вправо",
    "what_to_do": "стоп"
  },
  {
    "image_name": "image5127.png",
    "position_of_policman": "вправо",
    "what_to_do": "стоп"
  },
  {
    "image_name": "image5128.png",
    "position_of_policman": "вправо",
    "what_to_do": "стоп"
  },
  {
    "image_name": "image5129.png",
    "position_of_policman": "вправо",
    "what_to_do": "стоп"
  },
  {
    "image_name": "image5130.png",
    "position_of_policman": "вправо",
    "what_to_do": "стоп"
  },
  {
    "image_name": "image5131.png",
    "position_of_policman": "вправо",
    "what_to_do": "стоп"
  },
  {
    "image_name": "image5132.png",
    "position_of_policman": "вправо",
    "what_to_do": "стоп"
  },
  {
    "image_name": "image5133.png",
    "position_of_policman": "вправо",
    "what_to_do": "стоп"
  },
  {
    "image_name": "image5134.png",
    "position_of_policman": "вправо",
    "what_to_do": "стоп"
  },
  {
    "image_name": "image5135.png",
    "position_of_policman": "вправо",
    "what_to_do": "стоп"
  },
  {
    "image_name": "image5136.png",
    "position_of_policman": "вправо",
    "what_to_do": "стоп"
  },
  {
    "image_name": "image5137.png",
    "position_of_policman": "вправо",
    "what_to_do": "стоп"
  },
  {
    "image_name": "image5138.png",
    "position_of_policman": "вправо",
    "what_to_do": "стоп"
  },
  {
    "image_name": "image5139.png",
    "position_of_policman": "вправо",
    "what_to_do": "стоп"
  },
  {
    "image_name": "image5140.png",
    "position_of_policman": "вправо",
    "what_to_do": "стоп"
  },
  {
    "image_name": "image5141.png",
    "position_of_policman": "вправо",
    "what_to_do": "стоп"
  },
  {
    "image_name": "image5142.png",
    "position_of_policman": "вправо",
    "what_to_do": "стоп"
  },
  {
    "image_name": "image5143.png",
    "position_of_policman": "вправо",
    "what_to_do": "стоп"
  },
  {
    "image_name": "image5144.png",
    "position_of_policman": "вправо",
    "what_to_do": "стоп"
  },
  {
    "image_name": "image5145.png",
    "position_of_policman": "вправо",
    "what_to_do": "стоп"
  },
  {
    "image_name": "image5146.png",
    "position_of_policman": "вправо",
    "what_to_do": "стоп"
  },
  {
    "image_name": "image5147.png",
    "position_of_policman": "вправо",
    "what_to_do": "стоп"
  },
  {
    "image_name": "image5148.png",
    "position_of_policman": "вправо",
    "what_to_do": "стоп"
  },
  {
    "image_name": "image5149.png",
    "position_of_policman": "вправо",
    "what_to_do": "стоп"
  },
  {
    "image_name": "image5150.png",
    "position_of_policman": "вправо",
    "what_to_do": "стоп"
  },
  {
    "image_name": "image5151.png",
    "position_of_policman": "вправо",
    "what_to_do": "стоп"
  },
  {
    "image_name": "image5152.png",
    "position_of_policman": "вправо",
    "what_to_do": "стоп"
  },
  {
    "image_name": "image5153.png",
    "position_of_policman": "вправо",
    "what_to_do": "стоп"
  },
  {
    "image_name": "image5154.png",
    "position_of_policman": "вправо",
    "what_to_do": "стоп"
  },
  {
    "image_name": "image5155.png",
    "position_of_policman": "вправо",
    "what_to_do": "стоп"
  },
  {
    "image_name": "image5156.png",
    "position_of_policman": "вправо",
    "what_to_do": "стоп"
  },
  {
    "image_name": "image5157.png",
    "position_of_policman": "вправо",
    "what_to_do": "стоп"
  },
  {
    "image_name": "image5158.png",
    "position_of_policman": "вправо",
    "what_to_do": "стоп"
  },
  {
    "image_name": "image5159.png",
    "position_of_policman": "вправо",
    "what_to_do": "стоп"
  },
  {
    "image_name": "image5160.png",
    "position_of_policman": "вправо",
    "what_to_do": "стоп"
  },
  {
    "image_name": "image5161.png",
    "position_of_policman": "вправо",
    "what_to_do": "стоп"
  },
  {
    "image_name": "image5162.png",
    "position_of_policman": "вправо",
    "what_to_do": "стоп"
  },
  {
    "image_name": "image5163.png",
    "position_of_policman": "вправо",
    "what_to_do": "стоп"
  },
  {
    "image_name": "image5164.png",
    "position_of_policman": "вправо",
    "what_to_do": "стоп"
  },
  {
    "image_name": "image5165.png",
    "position_of_policman": "вправо",
    "what_to_do": "стоп"
  },
  {
    "image_name": "image5166.png",
    "position_of_policman": "вправо",
    "what_to_do": "стоп"
  },
  {
    "image_name": "image5167.png",
    "position_of_policman": "вправо",
    "what_to_do": "стоп"
  },
  {
    "image_name": "image5168.png",
    "position_of_policman": "вправо",
    "what_to_do": "стоп"
  },
  {
    "image_name": "image5169.png",
    "position_of_policman": "вправо",
    "what_to_do": "стоп"
  },
  {
    "image_name": "image5170.png",
    "position_of_policman": "вправо",
    "what_to_do": "стоп"
  },
  {
    "image_name": "image5171.png",
    "position_of_policman": "вправо",
    "what_to_do": "стоп"
  },
  {
    "image_name": "image5172.png",
    "position_of_policman": "вправо",
    "what_to_do": "стоп"
  },
  {
    "image_name": "image5173.png",
    "position_of_policman": "вправо",
    "what_to_do": "стоп"
  },
  {
    "image_name": "image5174.png",
    "position_of_policman": "вправо",
    "what_to_do": "стоп"
  },
  {
    "image_name": "image5175.png",
    "position_of_policman": "вправо",
    "what_to_do": "стоп"
  },
  {
    "image_name": "image5176.png",
    "position_of_policman": "вправо",
    "what_to_do": "стоп"
  },
  {
    "image_name": "image5177.png",
    "position_of_policman": "вправо",
    "what_to_do": "стоп"
  },
  {
    "image_name": "image5178.png",
    "position_of_policman": "вправо",
    "what_to_do": "стоп"
  },
  {
    "image_name": "image5179.png",
    "position_of_policman": "вправо",
    "what_to_do": "стоп"
  },
  {
    "image_name": "image5180.png",
    "position_of_policman": "вправо",
    "what_to_do": "стоп"
  },
  {
    "image_name": "image5181.png",
    "position_of_policman": "вправо",
    "what_to_do": "стоп"
  },
  {
    "image_name": "image5182.png",
    "position_of_policman": "вправо",
    "what_to_do": "стоп"
  },
  {
    "image_name": "image5183.png",
    "position_of_policman": "вправо",
    "what_to_do": "стоп"
  },
  {
    "image_name": "image5184.png",
    "position_of_policman": "вправо",
    "what_to_do": "стоп"
  },
  {
    "image_name": "image5185.png",
    "position_of_policman": "вправо",
    "what_to_do": "стоп"
  },
  {
    "image_name": "image5186.png",
    "position_of_policman": "вправо",
    "what_to_do": "стоп"
  },
  {
    "image_name": "image5187.png",
    "position_of_policman": "вправо",
    "what_to_do": "стоп"
  },
  {
    "image_name": "image5188.png",
    "position_of_policman": "вправо",
    "what_to_do": "стоп"
  },
  {
    "image_name": "image5189.png",
    "position_of_policman": "вправо",
    "what_to_do": "стоп"
  },
  {
    "image_name": "image5190.png",
    "position_of_policman": "вправо",
    "what_to_do": "стоп"
  },
  {
    "image_name": "image5191.png",
    "position_of_policman": "вправо",
    "what_to_do": "стоп"
  },
  {
    "image_name": "image5192.png",
    "position_of_policman": "вправо",
    "what_to_do": "стоп"
  },
  {
    "image_name": "image5193.png",
    "position_of_policman": "вправо",
    "what_to_do": "стоп"
  },
  {
    "image_name": "image5194.png",
    "position_of_policman": "вправо",
    "what_to_do": "стоп"
  },
  {
    "image_name": "image5195.png",
    "position_of_policman": "вправо",
    "what_to_do": "стоп"
  },
  {
    "image_name": "image5196.png",
    "position_of_policman": "вправо",
    "what_to_do": "стоп"
  },
  {
    "image_name": "image5197.png",
    "position_of_policman": "вправо",
    "what_to_do": "стоп"
  },
  {
    "image_name": "image5198.png",
    "position_of_policman": "вправо",
    "what_to_do": "стоп"
  },
  {
    "image_name": "image5199.png",
    "position_of_policman": "вправо",
    "what_to_do": "стоп"
  },
  {
    "image_name": "image5200.png",
    "position_of_policman": "вправо",
    "what_to_do": "стоп"
  },
  {
    "image_name": "trafficController.json",
    "position_of_policman": "вправо",
    "what_to_do": "стоп"
  }
]